ppprint/Color.py
ppprint/LogLevel.py
ppprint/__init__.py
ppprint/colorize.py
ppprint/config.py
ppprint/console.py
ppprint/lvlColor.py
ppprint/printer.py
ppprint/progress.py
ppprint-0.1.0.dist-info/LICENSE
ppprint-0.1.0.dist-info/METADATA
ppprint-0.1.0.dist-info/WHEEL
ppprint-0.1.0.dist-info/top_level.txt
ppprint-0.1.0.dist-info/RECORD
