Metadata-Version: 2.1
Name: ppprint
Version: 0.1.0
Summary: An easy to use Python Pretty Print
Home-page: https://github.com/sylvelk/ppprint
Author: Sylvain El-Khoury
Author-email: sylvelk@gmail.com
License: UNKNOWN
Project-URL: Bug Report, https://github.com/sylvelk/ppprint/issues/new?template=bug_report.md
Project-URL: Feature Request, https://github.com/sylvelk/ppprint/issues/new?template=feature_request.md
Project-URL: Documentation, https://github.com/sylvelk/ppprint/tree/master/ppprint
Project-URL: Source Code, https://github.com/sylvelk/ppprint
Keywords: print pretty console progress bar
Platform: UNKNOWN
Classifier: Programming Language :: Python :: 3
Classifier: License :: OSI Approved :: GNU General Public License v3 (GPLv3)
Classifier: Operating System :: OS Independent
Requires-Python: >=3.6
